tmcolors.py
tmcolors-0.1.1.dist-info/DESCRIPTION.rst
tmcolors-0.1.1.dist-info/METADATA
tmcolors-0.1.1.dist-info/metadata.json
tmcolors-0.1.1.dist-info/RECORD
tmcolors-0.1.1.dist-info/top_level.txt
tmcolors-0.1.1.dist-info/WHEEL
