Metadata-Version: 2.0
Name: tmcolors
Version: 0.1.1
Summary: ANSI colors for Python
Home-page: https://github.com/mysz/tmcolors
Author: Giorgos Verigakis, Marcin Sztolcman
Author-email: marcin@urzenia.net
License: ISC
Platform: UNKNOWN
Classifier: Environment :: Console
Classifier: Intended Audience :: Developers
Classifier: License :: OSI Approved :: ISC License (ISCL)
Classifier: Programming Language :: Python :: 2.6
Classifier: Programming Language :: Python :: 2.7
Classifier: Programming Language :: Python :: 3
